odoo8_addon_stock_analysis-8.0.1.0.0.99.dev1-py2.7-nspkg.pth
odoo8_addon_stock_analysis-8.0.1.0.0.99.dev1.dist-info/top_level.txt
odoo8_addon_stock_analysis-8.0.1.0.0.99.dev1.dist-info/WHEEL
odoo8_addon_stock_analysis-8.0.1.0.0.99.dev1.dist-info/RECORD
odoo8_addon_stock_analysis-8.0.1.0.0.99.dev1.dist-info/metadata.json
odoo8_addon_stock_analysis-8.0.1.0.0.99.dev1.dist-info/DESCRIPTION.rst
odoo8_addon_stock_analysis-8.0.1.0.0.99.dev1.dist-info/METADATA
odoo8_addon_stock_analysis-8.0.1.0.0.99.dev1.dist-info/namespace_packages.txt
odoo_addons/stock_analysis/__openerp__.py
odoo_addons/stock_analysis/__init__.py
odoo_addons/stock_analysis/README.rst
odoo_addons/stock_analysis/security/ir.model.access.csv
odoo_addons/stock_analysis/report/stock_analysis.py
odoo_addons/stock_analysis/report/stock_analysis_view.xml
odoo_addons/stock_analysis/report/__init__.py
odoo_addons/stock_analysis/images/demo_analysis.png
odoo_addons/stock_analysis/static/description/icon.png
